CHANGELOG.txt
LICENCE.txt
MANIFEST.in
README.txt
setup.py
coep_package/__init__.py
coep_package/credentials.json
coep_package/csv_module.py
coep_package/drive_api.py
coep_package/latex.py
coep_package.egg-info/PKG-INFO
coep_package.egg-info/SOURCES.txt
coep_package.egg-info/dependency_links.txt
coep_package.egg-info/requires.txt
coep_package.egg-info/top_level.txt