Metadata-Version: 1.1
Name: coep-package
Version: 0.1.3
Summary: to create csv file and create latex code
Home-page: UNKNOWN
Author: Rohan Pol
Author-email: rohanpol36@gmail.com
License: MIT
Keywords: coep
Platform: UNKNOWN
Classifier: Development Status :: 5 - Production/Stable
Classifier: Intended Audience :: Education
Classifier: Operating System :: Microsoft :: Windows :: Windows 10
Classifier: License :: OSI Approved :: MIT License
Classifier: Programming Language :: Python :: 3
